office2md/__init__.py
office2md/__version__.py
office2md/_version.py
office2md/cli.py
office2md/converter_factory.py
office2md/converters/__init__.py
office2md/converters/base_converter.py
office2md/converters/basic_docx_converter.py
office2md/converters/docling_converter.py
office2md/converters/docx_converter.py
office2md/converters/mammoth_converter.py
office2md/converters/pandoc_converter.py
office2md/converters/pptx_converter.py
office2md/converters/xlsx_converter.py
office2md-0.1.3.dist-info/licenses/LICENSE
office2md-0.1.3.dist-info/METADATA
office2md-0.1.3.dist-info/WHEEL
office2md-0.1.3.dist-info/entry_points.txt
office2md-0.1.3.dist-info/top_level.txt
office2md-0.1.3.dist-info/RECORD
