Metadata-Version: 2.4
Name: office2md
Version: 0.1.3
Summary: Convert Microsoft Office documents (DOCX, XLSX, PPTX) and PDFs to Markdown
Author-email: Your Name <your.email@example.com>
License: MIT
Project-URL: Homepage, https://github.com/yourusername/office2md
Project-URL: Documentation, https://github.com/yourusername/office2md#readme
Project-URL: Repository, https://github.com/yourusername/office2md.git
Project-URL: Issues, https://github.com/yourusername/office2md/issues
Project-URL: Changelog, https://github.com/yourusername/office2md/blob/main/CHANGELOG.md
Keywords: markdown,docx,xlsx,pptx,pdf,converter,office,word,excel,powerpoint
Classifier: Development Status :: 4 - Beta
Classifier: Intended Audience :: Developers
Classifier: License :: OSI Approved :: MIT License
Classifier: Operating System :: OS Independent
Classifier: Programming Language :: Python :: 3
Classifier: Programming Language :: Python :: 3.8
Classifier: Programming Language :: Python :: 3.9
Classifier: Programming Language :: Python :: 3.10
Classifier: Programming Language :: Python :: 3.11
Classifier: Programming Language :: Python :: 3.12
Classifier: Topic :: Text Processing :: Markup :: Markdown
Classifier: Topic :: Office/Business
Requires-Python: >=3.8
License-File: LICENSE
Requires-Dist: python-docx>=1.1.0
Requires-Dist: openpyxl>=3.1.0
Requires-Dist: python-pptx>=0.6.23
Requires-Dist: mammoth>=1.6.0
Requires-Dist: markdownify>=0.11.0
Requires-Dist: Pillow>=9.0.0
Provides-Extra: pdf
Requires-Dist: docling>=1.0.0; extra == "pdf"
Provides-Extra: dev
Requires-Dist: pytest>=7.0.0; extra == "dev"
Requires-Dist: pytest-cov>=4.0.0; extra == "dev"
Requires-Dist: black>=23.0.0; extra == "dev"
Requires-Dist: ruff>=0.1.0; extra == "dev"
Requires-Dist: mypy>=1.0.0; extra == "dev"
Provides-Extra: all
Requires-Dist: office2md[dev,pdf]; extra == "all"
Dynamic: license-file
